inspect_tools.py
meraki-mcp-dynamic.py
meraki-mcp.py
meraki_mcp_dynamic_impl.py
iflow_mcp_mkutka_meraki_magic_mcp-0.1.0.dist-info/licenses/LICENSE
iflow_mcp_mkutka_meraki_magic_mcp-0.1.0.dist-info/METADATA
iflow_mcp_mkutka_meraki_magic_mcp-0.1.0.dist-info/WHEEL
iflow_mcp_mkutka_meraki_magic_mcp-0.1.0.dist-info/entry_points.txt
iflow_mcp_mkutka_meraki_magic_mcp-0.1.0.dist-info/top_level.txt
iflow_mcp_mkutka_meraki_magic_mcp-0.1.0.dist-info/RECORD
