Metadata-Version: 2.4
Name: iflow-mcp_mkutka_meraki-magic-mcp
Version: 0.1.0
Summary: MCP Server for Cisco Meraki Dashboard API - provides tools for querying, monitoring, and managing Meraki environment
Requires-Python: >=3.8
License-File: LICENSE
Requires-Dist: mcp[cli]>=1.8.0
Requires-Dist: meraki>=2.0.2
Dynamic: license-file
